LICENSE
README.md
setup.py
ProyectoProgramacion/Circuito.py
ProyectoProgramacion/__init__.py
ProyectoProgramacion.egg-info/PKG-INFO
ProyectoProgramacion.egg-info/SOURCES.txt
ProyectoProgramacion.egg-info/dependency_links.txt
ProyectoProgramacion.egg-info/top_level.txt