Metadata-Version: 2.1
Name: ProyectoProgramacion
Version: 1.0.0
Summary: Esta es la descripcion de mi paquete
Home-page: https://github.com/CristianR746/CircuitoPrograma.git
Download-URL: https://github.com/CristianR746/CircuitoPrograma.git
Author: Cristian Rivera, Marcos David, Keren Pajon
Author-email: 
License: MIT
Keywords: testing,logging,example
License-File: LICENSE
